html_sanitizer/__init__.py
html_sanitizer/__main__.py
html_sanitizer/django.py
html_sanitizer/sanitizer.py
html_sanitizer/tests.py
html_sanitizer-2.5.0.dist-info/METADATA
html_sanitizer-2.5.0.dist-info/WHEEL
html_sanitizer-2.5.0.dist-info/licenses/LICENSE
html_sanitizer-2.5.0.dist-info/RECORD
